somanet_package_installer/__init__.py
somanet_package_installer-0.0.12.data/scripts/somanet-package-installer
somanet_package_installer-0.0.12.dist-info/LICENSE
somanet_package_installer-0.0.12.dist-info/METADATA
somanet_package_installer-0.0.12.dist-info/WHEEL
somanet_package_installer-0.0.12.dist-info/top_level.txt
somanet_package_installer-0.0.12.dist-info/RECORD
