Metadata-Version: 2.1
Name: somanet-package-installer
Version: 0.0.12
Summary: Install SOMANET motion drive package to an EtherCAT slave
Home-page: https://github.com/synapticon/somanet-package-installer
Author: Marko Sanković
Author-email: msankovic@synapticon.com
License: MIT
Platform: UNKNOWN
Classifier: Programming Language :: Python :: 3
Classifier: License :: OSI Approved :: MIT License
Classifier: Operating System :: POSIX :: Linux
